odoo/addons/ssi_reference_document_mixin/README.rst
odoo/addons/ssi_reference_document_mixin/__init__.py
odoo/addons/ssi_reference_document_mixin/__manifest__.py
odoo/addons/ssi_reference_document_mixin/menu.xml
odoo/addons/ssi_reference_document_mixin/demo/reference_document_category_demos.xml
odoo/addons/ssi_reference_document_mixin/demo/reference_document_demos.xml
odoo/addons/ssi_reference_document_mixin/models/__init__.py
odoo/addons/ssi_reference_document_mixin/models/mixin_reference_document.py
odoo/addons/ssi_reference_document_mixin/models/reference_document.py
odoo/addons/ssi_reference_document_mixin/models/reference_document_category.py
odoo/addons/ssi_reference_document_mixin/models/reference_document_set.py
odoo/addons/ssi_reference_document_mixin/security/ir.model.access.csv
odoo/addons/ssi_reference_document_mixin/static/description/icon.png
odoo/addons/ssi_reference_document_mixin/templates/mixin_reference_document_templates.xml
odoo/addons/ssi_reference_document_mixin/views/reference_document_category_views.xml
odoo/addons/ssi_reference_document_mixin/views/reference_document_set_views.xml
odoo/addons/ssi_reference_document_mixin/views/reference_document_views.xml
odoo14_addon_ssi_reference_document_mixin-14.0.2.1.0.dist-info/METADATA
odoo14_addon_ssi_reference_document_mixin-14.0.2.1.0.dist-info/WHEEL
odoo14_addon_ssi_reference_document_mixin-14.0.2.1.0.dist-info/top_level.txt
odoo14_addon_ssi_reference_document_mixin-14.0.2.1.0.dist-info/RECORD
